commit2doc/__init__.py
commit2doc-0.0.0.dist-info/METADATA
commit2doc-0.0.0.dist-info/WHEEL
commit2doc-0.0.0.dist-info/licenses/LICENSE
commit2doc-0.0.0.dist-info/RECORD
