Metadata-Version: 2.4
Name: commit2doc
Version: 0.0.0
Summary: TODO
Project-URL: homepage, https://github.com/kaycebasques/commit2doc
Project-URL: issues, https://github.com/kaycebasques/commit2doc/issues
Author-email: Kayce Basques <kaycebasques@gmail.com>
License-File: LICENSE
Requires-Python: >=3.12
Provides-Extra: gemini
Requires-Dist: google-genai==1.53.0; extra == 'gemini'
